javaproperties_cli/__init__.py
javaproperties_cli/__main__.py
javaproperties_cli/fromjson.py
javaproperties_cli/tojson.py
javaproperties_cli/util.py
javaproperties_cli-0.8.2.dist-info/METADATA
javaproperties_cli-0.8.2.dist-info/WHEEL
javaproperties_cli-0.8.2.dist-info/entry_points.txt
javaproperties_cli-0.8.2.dist-info/licenses/LICENSE
javaproperties_cli-0.8.2.dist-info/RECORD
