Metadata-Version: 2.4
Name: javaproperties-cli
Version: 0.8.2
Summary: Command-line manipulation of Java .properties files
Project-URL: Source Code, https://github.com/jwodder/javaproperties-cli
Project-URL: Bug Tracker, https://github.com/jwodder/javaproperties-cli/issues
Project-URL: Documentation, https://javaproperties-cli.readthedocs.io
Author-email: John Thorvald Wodder II <javaproperties-cli@varonathe.org>
License-Expression: MIT
License-File: LICENSE
Keywords: config,configfile,configuration,java,javaproperties,properties
Classifier: Environment :: Console
Classifier: Intended Audience :: Developers
Classifier: Programming Language :: Python :: 3
Classifier: Programming Language :: Python :: 3 :: Only
Classifier: Programming Language :: Python :: 3.10
Classifier: Programming Language :: Python :: 3.11
Classifier: Programming Language :: Python :: 3.12
Classifier: Programming Language :: Python :: 3.13
Classifier: Programming Language :: Python :: Implementation :: CPython
Classifier: Programming Language :: Python :: Implementation :: PyPy
Classifier: Topic :: Software Development
Classifier: Topic :: Software Development :: Libraries :: Java Libraries
Classifier: Topic :: Utilities
Requires-Python: >=3.10
Requires-Dist: click~=8.2
Requires-Dist: javaproperties<0.9,>=0.7.0
